term_cast.py
mobile_terminal-0.2.1.dist-info/licenses/LICENSE
mobile_terminal-0.2.1.dist-info/METADATA
mobile_terminal-0.2.1.dist-info/WHEEL
mobile_terminal-0.2.1.dist-info/entry_points.txt
mobile_terminal-0.2.1.dist-info/top_level.txt
mobile_terminal-0.2.1.dist-info/RECORD
